pyempaq/__init__.py
pyempaq/__main__.py
pyempaq/_version.py
pyempaq/common.py
pyempaq/config_manager.py
pyempaq/main.py
pyempaq/unpacker.py
pyempaq-0.6.0.dist-info/LICENSE
pyempaq-0.6.0.dist-info/METADATA
pyempaq-0.6.0.dist-info/WHEEL
pyempaq-0.6.0.dist-info/entry_points.txt
pyempaq-0.6.0.dist-info/top_level.txt
pyempaq-0.6.0.dist-info/RECORD
