Metadata-Version: 2.1
Name: pyempaq
Version: 0.6.0
Summary: A Python packer to run anywhwere any project with any virtualenv dependencies.
Home-page: https://github.com/facundobatista/pyempaq
Author: Facundo Batista
Author-email: facundo@taniquetil.com.ar
License: GPL-v3
Platform: UNKNOWN
Classifier: Environment :: Console
Classifier: License :: OSI Approved :: GNU General Public License v3 (GPLv3)
Classifier: Operating System :: OS Independent
Classifier: Programming Language :: Python :: 3
Classifier: Topic :: System :: Archiving :: Packaging
Classifier: Topic :: System :: Software Distribution
Requires-Python: >=3.9
License-File: LICENSE
Requires-Dist: PyYAML (==6.0.1)
Requires-Dist: pydantic (==2.5.3)
